yfinance/__init__.py
yfinance/base.py
yfinance/cache.py
yfinance/const.py
yfinance/data.py
yfinance/exceptions.py
yfinance/multi.py
yfinance/shared.py
yfinance/ticker.py
yfinance/tickers.py
yfinance/utils.py
yfinance/version.py
yfinance/domain/__init__.py
yfinance/domain/domain.py
yfinance/domain/industry.py
yfinance/domain/sector.py
yfinance/scrapers/__init__.py
yfinance/scrapers/analysis.py
yfinance/scrapers/fundamentals.py
yfinance/scrapers/funds.py
yfinance/scrapers/history.py
yfinance/scrapers/holders.py
yfinance/scrapers/quote.py
yfinance/screener/__init__.py
yfinance/screener/screener.py
yfinance/screener/screener_query.py
yfinance-0.2.50.dist-info/LICENSE.txt
yfinance-0.2.50.dist-info/METADATA
yfinance-0.2.50.dist-info/WHEEL
yfinance-0.2.50.dist-info/entry_points.txt
yfinance-0.2.50.dist-info/top_level.txt
yfinance-0.2.50.dist-info/RECORD
